pyfunmath/__init__.py
pyfunmath/core.py
pyfunmath-0.1.0.dist-info/licenses/LICENSE
pyfunmath-0.1.0.dist-info/METADATA
pyfunmath-0.1.0.dist-info/WHEEL
pyfunmath-0.1.0.dist-info/top_level.txt
pyfunmath-0.1.0.dist-info/RECORD
